[
    {
        "host": "61.181.203.13",
        "port": 80
    },
    {
        "host": "msfwifi.3g.qq.com",
        "port": 8080
    },
    {
        "host": "221.198.69.95",
        "port": 80
    },
    {
        "host": "221.198.69.46",
        "port": 80
    },
    {
        "host": "153.3.50.212",
        "port": 14000
    },
    {
        "host": "221.198.69.77",
        "port": 443
    },
    {
        "host": "153.3.50.20",
        "port": 80
    },
    {
        "host": "157.255.13.227",
        "port": 8080
    },
    {
        "host": "157.255.13.77",
        "port": 443
    },
    {
        "host": "153.3.149.48",
        "port": 8080
    }
]